[{"defaultsidebar":["iva_bk_widget-2","recent-posts-2","recent-comments-2","archives-2","categories-2"],"heaer_right_area":["text-2","iva_business_hrs-2"],"topbarleft":["text-3"],"topbarright":["sociable_widget-3"],"footer_leftcopyright":["text-4"],"footer_rightcopyright":["text-5"],"footercolumn1":["contactinfo_widgets-2"],"footercolumn2":["nav_menu-2"],"footercolumn3":["nav_menu-3"],"footercolumn4":["contactinfo_widgets-3"]},{"iva_bk_widget":{"2":{"iva_bk_title":"Get Bookings for Services!","iva_bk_desc":"Short summary for the text.","iva_bk_btn_txt":"Make Booking","iva_extracss":""},"_multiwidget":1},"recent-posts":{"2":{"title":"","number":5},"_multiwidget":1},"recent-comments":{"2":{"title":"","number":5},"_multiwidget":1},"archives":{"2":{"title":"","count":0,"dropdown":0},"_multiwidget":1},"categories":{"2":{"title":"","count":0,"hierarchical":0,"dropdown":0},"_multiwidget":1},"text":{"2":{"title":"","text":"<strong><a href=\"#\">Make an Appointment<\/a> | Call : 123-456-7890<\/strong>","filter":false,"iva_extracss":""},"3":{"title":"","text":"Make an Appointment | Call : 123-456-7890","filter":false,"iva_extracss":""},"4":{"title":"","text":"\u00a9 Carzone.com, 2015","filter":false,"iva_extracss":""},"5":{"title":"","text":"Powered by Carzone.com - WordPress","filter":false,"iva_extracss":""},"_multiwidget":1},"iva_business_hrs":{"2":{"iva_bhrs_title":"","iva_bhrs_id":"","iva_bhrs_class":"","iva_extracss":""},"_multiwidget":1},"sociable_widget":{"3":{"title":"","color":"black","iva_extracss":""},"_multiwidget":1},"contactinfo_widgets":{"2":{"contactinfo_title":"Locate Us","syscontact_name":"Autotow Postal Address","syscontact_address":"PO Box 15142 Collins Street West\r\n120 King Street, Melbourne\r\nVictoria 2000 Australia","syscontact_email":"yourname@domain.com","syscontact_phone":"+61 0 1234 0000","syscontact_websiteurl":"","iva_extracss":""},"3":{"contactinfo_title":"Get in touch!","syscontact_name":"Auto Tow Headquarters","syscontact_address":"PO Box 15142 Collins Street West\r\nVictoria 2007 Australia\r\nAnona Headquarters","syscontact_email":"yourname(@)domain.com","syscontact_phone":"(+00) 0123-456-798","syscontact_websiteurl":"","iva_extracss":"textright"},"_multiwidget":1},"nav_menu":{"2":{"title":"Customer Services","nav_menu":20,"iva_extracss":"footermenu textright"},"3":{"title":"Company Information","nav_menu":21,"iva_extracss":"footermenu textleft"},"_multiwidget":1}}]